songs_dl/__init__.py
songs_dl/__main__.py
songs_dl/deezer.py
songs_dl/itunes.py
songs_dl/monkeypatch_requests.py
songs_dl/musixmatch.py
songs_dl/print_lyrics.py
songs_dl/spotify.py
songs_dl/utils.py
songs_dl/youtube.py
songs_dl/youtube_dl.py
songs_dl-2024.8.16.dist-info/LICENSE
songs_dl-2024.8.16.dist-info/METADATA
songs_dl-2024.8.16.dist-info/WHEEL
songs_dl-2024.8.16.dist-info/entry_points.txt
songs_dl-2024.8.16.dist-info/top_level.txt
songs_dl-2024.8.16.dist-info/RECORD
