Metadata-Version: 2.1
Name: songs-dl
Version: 2024.8.16
Summary: Download songs on YouTube and add metadata.
Author-email: Laurent FAVOLE <laurentfavole03@gmail.com>
License: This is free and unencumbered software released into the public domain.
Project-URL: Homepage, https://github.com/lfavole/songs-dl
Keywords: youtube,music
Classifier: Development Status :: 4 - Beta
Classifier: Environment :: Console
Classifier: License :: Public Domain
Classifier: Programming Language :: Python
Classifier: Programming Language :: Python :: 3
Classifier: Topic :: Multimedia :: Sound/Audio
Requires-Python: >=3.7
License-File: LICENSE
Requires-Dist: fpdf2
Requires-Dist: mutagen
Requires-Dist: Pillow
Requires-Dist: rapidfuzz
Requires-Dist: requests
Requires-Dist: tqdm
Requires-Dist: Unidecode
Requires-Dist: yt-dlp
Provides-Extra: build
Requires-Dist: build; extra == "build"
Requires-Dist: pyinstaller; extra == "build"
Requires-Dist: twine; extra == "build"
Provides-Extra: dev
Requires-Dist: black; extra == "dev"
Requires-Dist: bumpver; extra == "dev"
Requires-Dist: flake8; extra == "dev"
Requires-Dist: isort; extra == "dev"
Requires-Dist: pylint; extra == "dev"
Provides-Extra: docs
Requires-Dist: markdown-include; extra == "docs"
Requires-Dist: mkdocs; extra == "docs"
Requires-Dist: mkdocs-material; extra == "docs"
Requires-Dist: mkdocs-minify-plugin; extra == "docs"
